demo/demo_svr.py
demo/session_test_demo.py
session_tester/__init__.py
session_tester/client.py
session_tester/decorator.py
session_tester/logger.py
session_tester/request.py
session_tester/session.py
session_tester/session_maintainer.py
session_tester/test_suite.py
session_tester/testcase.py
session_tester/tester.py
session_tester/user_info.py
session_tester/utils.py
session_tester/cases/__init__.py
session_tester/cases/common.py
session_tester/cases/dist_stat.py
session_tester-0.1.0.dev20.dist-info/licenses/LICENSE
session_tester-0.1.0.dev20.dist-info/METADATA
session_tester-0.1.0.dev20.dist-info/WHEEL
session_tester-0.1.0.dev20.dist-info/top_level.txt
session_tester-0.1.0.dev20.dist-info/RECORD
