Metadata-Version: 2.4
Name: session_tester
Version: 0.1.0.dev20
Summary: Session Tester Python package
Author-email: Pan Zhongxian <panzhongxian0532@gmail.com>
License: MIT
Project-URL: Homepage, https://github.com/session-tester/session-tester
Project-URL: Documentation, https://github.com/session-tester
Project-URL: Source Code, https://github.com/session-tester/session-tester
Classifier: Programming Language :: Python :: 3
Classifier: License :: OSI Approved :: MIT License
Classifier: Operating System :: OS Independent
Requires-Python: >=3.6
License-File: LICENSE
Requires-Dist: openpyxl>=3.1.3
Requires-Dist: pandas>=2.2.3
Requires-Dist: xlsxwriter>=3.2.0
Requires-Dist: requests>=2.32.3
Dynamic: license-file
